refineo_cli/__init__.py
refineo_cli/api.py
refineo_cli/cli.py
refineo_cli/config.py
refineo_cli-0.1.1.dist-info/METADATA
refineo_cli-0.1.1.dist-info/WHEEL
refineo_cli-0.1.1.dist-info/entry_points.txt
refineo_cli-0.1.1.dist-info/RECORD
