Metadata-Version: 2.4
Name: refineo-cli
Version: 0.1.1
Summary: Refineo AI Text Humanizer CLI - Transform AI-generated text into natural human writing
Project-URL: Homepage, https://www.refineo.app
Author: Refineo
License-Expression: MIT
Keywords: ai,cli,humanizer,mcp,refineo,text,writing
Classifier: Development Status :: 4 - Beta
Classifier: Intended Audience :: Developers
Classifier: License :: OSI Approved :: MIT License
Classifier: Programming Language :: Python :: 3
Classifier: Programming Language :: Python :: 3.10
Classifier: Programming Language :: Python :: 3.11
Classifier: Programming Language :: Python :: 3.12
Classifier: Programming Language :: Python :: 3.13
Classifier: Topic :: Software Development :: Libraries :: Python Modules
Classifier: Topic :: Text Processing
Requires-Python: >=3.10
Provides-Extra: dev
Requires-Dist: mypy>=1.13.0; extra == 'dev'
Requires-Dist: pytest>=8.0.0; extra == 'dev'
Requires-Dist: ruff>=0.8.0; extra == 'dev'
